pysec_downloader/__init__.py
pysec_downloader/_constants.py
pysec_downloader/downloader.py
pysec_downloader-0.0.47.dist-info/LICENSE
pysec_downloader-0.0.47.dist-info/METADATA
pysec_downloader-0.0.47.dist-info/WHEEL
pysec_downloader-0.0.47.dist-info/top_level.txt
pysec_downloader-0.0.47.dist-info/RECORD
