Metadata-Version: 2.1
Name: pysec-downloader
Version: 0.0.47
Summary: sec/edgar file downloader
Home-page: https://github.com/Camelket/pysec_downloader
Author: camelket
Author-email: camelket.develop@gmail.com
Project-URL: Bug Tracker, https://github.com/Camelket/pysec_downloader/issues
Classifier: Programming Language :: Python :: 3
Classifier: License :: OSI Approved :: MIT License
Classifier: Operating System :: OS Independent
Requires-Python: >=3.9
License-File: LICENSE
